{
  "run_config": {
    "num_streams": 4,
    "duration_minutes": 1.0,
    "segment_sec": 10.0,
    "batch_size": 1,
    "total_elapsed_sec": 160.314
  },
  "segments": [
    {
      "video_id": "RTSP_01",
      "filename": "RTSP_01_0.mp4",
      "segment_sec": 10.0,
      "queue_to_db_sec": 0.052,
      "success": false,
      "time_sec": 0,
      "vlm_time_sec": null,
      "yolo_reid_time_sec": null,
      "put_time_sec": 1773065272.051,
      "batch_upload_start_sec": 1773065272.051,
      "batch_upload_end_sec": 1773065272.103,
      "wait_in_queue_sec": 0.0,
      "client_upload_plus_backend_sec": 0.052,
      "api_batch_process_time_sec": null,
      "api_batch_total_time_sec": null,
      "time_breakdown": "queue_to_db_sec = wait_in_queue_sec + client_upload_plus_backend_sec (失敗批次). wait_in_queue_sec=0.0, client_upload_plus_backend_sec=0.052"
    },
    {
      "video_id": "RTSP_02",
      "filename": "RTSP_02_0.mp4",
      "segment_sec": 10.0,
      "queue_to_db_sec": 0.133,
      "success": false,
      "time_sec": 0,
      "vlm_time_sec": null,
      "yolo_reid_time_sec": null,
      "put_time_sec": 1773065272.034,
      "batch_upload_start_sec": 1773065272.034,
      "batch_upload_end_sec": 1773065272.167,
      "wait_in_queue_sec": 0.0,
      "client_upload_plus_backend_sec": 0.133,
      "api_batch_process_time_sec": null,
      "api_batch_total_time_sec": null,
      "time_breakdown": "queue_to_db_sec = wait_in_queue_sec + client_upload_plus_backend_sec (失敗批次). wait_in_queue_sec=0.0, client_upload_plus_backend_sec=0.133"
    },
    {
      "video_id": "RTSP_03",
      "filename": "RTSP_03_0.mp4",
      "segment_sec": 10.0,
      "queue_to_db_sec": 0.152,
      "success": false,
      "time_sec": 0,
      "vlm_time_sec": null,
      "yolo_reid_time_sec": null,
      "put_time_sec": 1773065272.035,
      "batch_upload_start_sec": 1773065272.035,
      "batch_upload_end_sec": 1773065272.187,
      "wait_in_queue_sec": 0.0,
      "client_upload_plus_backend_sec": 0.152,
      "api_batch_process_time_sec": null,
      "api_batch_total_time_sec": null,
      "time_breakdown": "queue_to_db_sec = wait_in_queue_sec + client_upload_plus_backend_sec (失敗批次). wait_in_queue_sec=0.0, client_upload_plus_backend_sec=0.152"
    },
    {
      "video_id": "RTSP_04",
      "filename": "RTSP_04_0.mp4",
      "segment_sec": 10.0,
      "queue_to_db_sec": 0.071,
      "success": false,
      "time_sec": 0,
      "vlm_time_sec": null,
      "yolo_reid_time_sec": null,
      "put_time_sec": 1773065272.165,
      "batch_upload_start_sec": 1773065272.165,
      "batch_upload_end_sec": 1773065272.236,
      "wait_in_queue_sec": 0.0,
      "client_upload_plus_backend_sec": 0.071,
      "api_batch_process_time_sec": null,
      "api_batch_total_time_sec": null,
      "time_breakdown": "queue_to_db_sec = wait_in_queue_sec + client_upload_plus_backend_sec (失敗批次). wait_in_queue_sec=0.0, client_upload_plus_backend_sec=0.071"
    },
    {
      "video_id": "RTSP_03",
      "filename": "RTSP_03_1.mp4",
      "segment_sec": 10.0,
      "queue_to_db_sec": 0.118,
      "success": false,
      "time_sec": 0,
      "vlm_time_sec": null,
      "yolo_reid_time_sec": null,
      "put_time_sec": 1773065285.613,
      "batch_upload_start_sec": 1773065285.613,
      "batch_upload_end_sec": 1773065285.731,
      "wait_in_queue_sec": 0.0,
      "client_upload_plus_backend_sec": 0.118,
      "api_batch_process_time_sec": null,
      "api_batch_total_time_sec": null,
      "time_breakdown": "queue_to_db_sec = wait_in_queue_sec + client_upload_plus_backend_sec (失敗批次). wait_in_queue_sec=0.0, client_upload_plus_backend_sec=0.118"
    },
    {
      "video_id": "RTSP_04",
      "filename": "RTSP_04_1.mp4",
      "segment_sec": 10.0,
      "queue_to_db_sec": 0.128,
      "success": false,
      "time_sec": 0,
      "vlm_time_sec": null,
      "yolo_reid_time_sec": null,
      "put_time_sec": 1773065285.615,
      "batch_upload_start_sec": 1773065285.615,
      "batch_upload_end_sec": 1773065285.743,
      "wait_in_queue_sec": 0.0,
      "client_upload_plus_backend_sec": 0.128,
      "api_batch_process_time_sec": null,
      "api_batch_total_time_sec": null,
      "time_breakdown": "queue_to_db_sec = wait_in_queue_sec + client_upload_plus_backend_sec (失敗批次). wait_in_queue_sec=0.0, client_upload_plus_backend_sec=0.128"
    },
    {
      "video_id": "RTSP_02",
      "filename": "RTSP_02_1.mp4",
      "segment_sec": 10.0,
      "queue_to_db_sec": 0.248,
      "success": false,
      "time_sec": 0,
      "vlm_time_sec": null,
      "yolo_reid_time_sec": null,
      "put_time_sec": 1773065285.611,
      "batch_upload_start_sec": 1773065285.611,
      "batch_upload_end_sec": 1773065285.859,
      "wait_in_queue_sec": 0.0,
      "client_upload_plus_backend_sec": 0.248,
      "api_batch_process_time_sec": null,
      "api_batch_total_time_sec": null,
      "time_breakdown": "queue_to_db_sec = wait_in_queue_sec + client_upload_plus_backend_sec (失敗批次). wait_in_queue_sec=0.0, client_upload_plus_backend_sec=0.248"
    },
    {
      "video_id": "RTSP_01",
      "filename": "RTSP_01_1.mp4",
      "segment_sec": 10.0,
      "queue_to_db_sec": 0.25,
      "success": false,
      "time_sec": 0,
      "vlm_time_sec": null,
      "yolo_reid_time_sec": null,
      "put_time_sec": 1773065285.609,
      "batch_upload_start_sec": 1773065285.609,
      "batch_upload_end_sec": 1773065285.859,
      "wait_in_queue_sec": 0.0,
      "client_upload_plus_backend_sec": 0.25,
      "api_batch_process_time_sec": null,
      "api_batch_total_time_sec": null,
      "time_breakdown": "queue_to_db_sec = wait_in_queue_sec + client_upload_plus_backend_sec (失敗批次). wait_in_queue_sec=0.0, client_upload_plus_backend_sec=0.25"
    },
    {
      "video_id": "RTSP_04",
      "filename": "RTSP_04_4.mp4",
      "segment_sec": 10.0,
      "queue_to_db_sec": 89.67,
      "success": false,
      "time_sec": 87.26,
      "vlm_time_sec": 0.0,
      "yolo_reid_time_sec": 0.0,
      "put_time_sec": 1773065326.686,
      "batch_upload_start_sec": 1773065326.686,
      "batch_upload_end_sec": 1773065416.355,
      "wait_in_queue_sec": 0.0,
      "client_upload_plus_backend_sec": 89.669,
      "api_batch_process_time_sec": 87.54,
      "api_batch_total_time_sec": 87.88,
      "time_breakdown": "queue_to_db_sec = wait_in_queue_sec + client_upload_plus_backend_sec (0.0 + 89.669 = 89.67). time_sec = 後端該段 total_api_time（同一批內多段共用同一批處理時間）。"
    },
    {
      "video_id": "RTSP_01",
      "filename": "RTSP_01_5.mp4",
      "segment_sec": 10.0,
      "queue_to_db_sec": 76.766,
      "success": false,
      "time_sec": 74.99,
      "vlm_time_sec": 0.0,
      "yolo_reid_time_sec": 0.0,
      "put_time_sec": 1773065340.412,
      "batch_upload_start_sec": 1773065340.412,
      "batch_upload_end_sec": 1773065417.178,
      "wait_in_queue_sec": 0.0,
      "client_upload_plus_backend_sec": 76.766,
      "api_batch_process_time_sec": 75.52,
      "api_batch_total_time_sec": 75.53,
      "time_breakdown": "queue_to_db_sec = wait_in_queue_sec + client_upload_plus_backend_sec (0.0 + 76.766 = 76.766). time_sec = 後端該段 total_api_time（同一批內多段共用同一批處理時間）。"
    },
    {
      "video_id": "RTSP_04",
      "filename": "RTSP_04_5.mp4",
      "segment_sec": 10.0,
      "queue_to_db_sec": 76.955,
      "success": false,
      "time_sec": 74.99,
      "vlm_time_sec": 0.0,
      "yolo_reid_time_sec": 0.0,
      "put_time_sec": 1773065340.226,
      "batch_upload_start_sec": 1773065340.226,
      "batch_upload_end_sec": 1773065417.18,
      "wait_in_queue_sec": 0.0,
      "client_upload_plus_backend_sec": 76.955,
      "api_batch_process_time_sec": 75.53,
      "api_batch_total_time_sec": 75.54,
      "time_breakdown": "queue_to_db_sec = wait_in_queue_sec + client_upload_plus_backend_sec (0.0 + 76.955 = 76.955). time_sec = 後端該段 total_api_time（同一批內多段共用同一批處理時間）。"
    },
    {
      "video_id": "RTSP_01",
      "filename": "RTSP_01_3.mp4",
      "segment_sec": 10.0,
      "queue_to_db_sec": 104.532,
      "success": false,
      "time_sec": 103.8,
      "vlm_time_sec": 0.0,
      "yolo_reid_time_sec": 0.0,
      "put_time_sec": 1773065312.905,
      "batch_upload_start_sec": 1773065312.905,
      "batch_upload_end_sec": 1773065417.438,
      "wait_in_queue_sec": 0.0,
      "client_upload_plus_backend_sec": 104.532,
      "api_batch_process_time_sec": 104.06,
      "api_batch_total_time_sec": 104.06,
      "time_breakdown": "queue_to_db_sec = wait_in_queue_sec + client_upload_plus_backend_sec (0.0 + 104.532 = 104.532). time_sec = 後端該段 total_api_time（同一批內多段共用同一批處理時間）。"
    },
    {
      "video_id": "RTSP_01",
      "filename": "RTSP_01_2.mp4",
      "segment_sec": 10.0,
      "queue_to_db_sec": 118.044,
      "success": false,
      "time_sec": 117.35,
      "vlm_time_sec": 0.0,
      "yolo_reid_time_sec": 0.0,
      "put_time_sec": 1773065299.394,
      "batch_upload_start_sec": 1773065299.395,
      "batch_upload_end_sec": 1773065417.439,
      "wait_in_queue_sec": 0.0,
      "client_upload_plus_backend_sec": 118.044,
      "api_batch_process_time_sec": 117.61,
      "api_batch_total_time_sec": 117.7,
      "time_breakdown": "queue_to_db_sec = wait_in_queue_sec + client_upload_plus_backend_sec (0.0 + 118.044 = 118.044). time_sec = 後端該段 total_api_time（同一批內多段共用同一批處理時間）。"
    },
    {
      "video_id": "RTSP_04",
      "filename": "RTSP_04_3.mp4",
      "segment_sec": 10.0,
      "queue_to_db_sec": 105.525,
      "success": false,
      "time_sec": 104.23,
      "vlm_time_sec": 0.0,
      "yolo_reid_time_sec": 0.0,
      "put_time_sec": 1773065312.955,
      "batch_upload_start_sec": 1773065312.955,
      "batch_upload_end_sec": 1773065418.48,
      "wait_in_queue_sec": 0.0,
      "client_upload_plus_backend_sec": 105.525,
      "api_batch_process_time_sec": 104.74,
      "api_batch_total_time_sec": 104.75,
      "time_breakdown": "queue_to_db_sec = wait_in_queue_sec + client_upload_plus_backend_sec (0.0 + 105.525 = 105.525). time_sec = 後端該段 total_api_time（同一批內多段共用同一批處理時間）。"
    },
    {
      "video_id": "RTSP_02",
      "filename": "RTSP_02_3.mp4",
      "segment_sec": 10.0,
      "queue_to_db_sec": 105.576,
      "success": false,
      "time_sec": 104.33,
      "vlm_time_sec": 0.0,
      "yolo_reid_time_sec": 0.0,
      "put_time_sec": 1773065312.905,
      "batch_upload_start_sec": 1773065312.905,
      "batch_upload_end_sec": 1773065418.481,
      "wait_in_queue_sec": 0.0,
      "client_upload_plus_backend_sec": 105.576,
      "api_batch_process_time_sec": 104.84,
      "api_batch_total_time_sec": 104.84,
      "time_breakdown": "queue_to_db_sec = wait_in_queue_sec + client_upload_plus_backend_sec (0.0 + 105.576 = 105.576). time_sec = 後端該段 total_api_time（同一批內多段共用同一批處理時間）。"
    },
    {
      "video_id": "RTSP_02",
      "filename": "RTSP_02_2.mp4",
      "segment_sec": 10.0,
      "queue_to_db_sec": 119.089,
      "success": false,
      "time_sec": 118.12,
      "vlm_time_sec": 0.0,
      "yolo_reid_time_sec": 0.0,
      "put_time_sec": 1773065299.394,
      "batch_upload_start_sec": 1773065299.394,
      "batch_upload_end_sec": 1773065418.483,
      "wait_in_queue_sec": 0.0,
      "client_upload_plus_backend_sec": 119.089,
      "api_batch_process_time_sec": 118.65,
      "api_batch_total_time_sec": 118.74,
      "time_breakdown": "queue_to_db_sec = wait_in_queue_sec + client_upload_plus_backend_sec (0.0 + 119.089 = 119.089). time_sec = 後端該段 total_api_time（同一批內多段共用同一批處理時間）。"
    },
    {
      "video_id": "RTSP_02",
      "filename": "RTSP_02_5.mp4",
      "segment_sec": 10.0,
      "queue_to_db_sec": 78.225,
      "success": false,
      "time_sec": 76.56,
      "vlm_time_sec": 0.0,
      "yolo_reid_time_sec": 0.0,
      "put_time_sec": 1773065340.258,
      "batch_upload_start_sec": 1773065340.258,
      "batch_upload_end_sec": 1773065418.483,
      "wait_in_queue_sec": 0.0,
      "client_upload_plus_backend_sec": 78.225,
      "api_batch_process_time_sec": 77.09,
      "api_batch_total_time_sec": 77.1,
      "time_breakdown": "queue_to_db_sec = wait_in_queue_sec + client_upload_plus_backend_sec (0.0 + 78.225 = 78.225). time_sec = 後端該段 total_api_time（同一批內多段共用同一批處理時間）。"
    },
    {
      "video_id": "RTSP_03",
      "filename": "RTSP_03_3.mp4",
      "segment_sec": 10.0,
      "queue_to_db_sec": 105.779,
      "success": false,
      "time_sec": 105.27,
      "vlm_time_sec": 0.0,
      "yolo_reid_time_sec": 0.0,
      "put_time_sec": 1773065312.98,
      "batch_upload_start_sec": 1773065312.98,
      "batch_upload_end_sec": 1773065418.758,
      "wait_in_queue_sec": 0.0,
      "client_upload_plus_backend_sec": 105.779,
      "api_batch_process_time_sec": 105.54,
      "api_batch_total_time_sec": 105.54,
      "time_breakdown": "queue_to_db_sec = wait_in_queue_sec + client_upload_plus_backend_sec (0.0 + 105.779 = 105.779). time_sec = 後端該段 total_api_time（同一批內多段共用同一批處理時間）。"
    },
    {
      "video_id": "RTSP_04",
      "filename": "RTSP_04_2.mp4",
      "segment_sec": 10.0,
      "queue_to_db_sec": 119.682,
      "success": false,
      "time_sec": 118.93,
      "vlm_time_sec": 0.0,
      "yolo_reid_time_sec": 0.0,
      "put_time_sec": 1773065299.345,
      "batch_upload_start_sec": 1773065299.345,
      "batch_upload_end_sec": 1773065419.027,
      "wait_in_queue_sec": 0.0,
      "client_upload_plus_backend_sec": 119.682,
      "api_batch_process_time_sec": 119.2,
      "api_batch_total_time_sec": 119.3,
      "time_breakdown": "queue_to_db_sec = wait_in_queue_sec + client_upload_plus_backend_sec (0.0 + 119.682 = 119.682). time_sec = 後端該段 total_api_time（同一批內多段共用同一批處理時間）。"
    },
    {
      "video_id": "RTSP_03",
      "filename": "RTSP_03_4.mp4",
      "segment_sec": 10.0,
      "queue_to_db_sec": 92.703,
      "success": false,
      "time_sec": 90.24,
      "vlm_time_sec": 0.0,
      "yolo_reid_time_sec": 0.0,
      "put_time_sec": 1773065326.586,
      "batch_upload_start_sec": 1773065326.586,
      "batch_upload_end_sec": 1773065419.289,
      "wait_in_queue_sec": 0.0,
      "client_upload_plus_backend_sec": 92.703,
      "api_batch_process_time_sec": 90.5,
      "api_batch_total_time_sec": 90.82,
      "time_breakdown": "queue_to_db_sec = wait_in_queue_sec + client_upload_plus_backend_sec (0.0 + 92.703 = 92.703). time_sec = 後端該段 total_api_time（同一批內多段共用同一批處理時間）。"
    },
    {
      "video_id": "RTSP_01",
      "filename": "RTSP_01_4.mp4",
      "segment_sec": 10.0,
      "queue_to_db_sec": 93.039,
      "success": false,
      "time_sec": 90.61,
      "vlm_time_sec": 0.0,
      "yolo_reid_time_sec": 0.0,
      "put_time_sec": 1773065326.532,
      "batch_upload_start_sec": 1773065326.532,
      "batch_upload_end_sec": 1773065419.571,
      "wait_in_queue_sec": 0.0,
      "client_upload_plus_backend_sec": 93.039,
      "api_batch_process_time_sec": 90.89,
      "api_batch_total_time_sec": 92.04,
      "time_breakdown": "queue_to_db_sec = wait_in_queue_sec + client_upload_plus_backend_sec (0.0 + 93.039 = 93.039). time_sec = 後端該段 total_api_time（同一批內多段共用同一批處理時間）。"
    },
    {
      "video_id": "RTSP_02",
      "filename": "RTSP_02_4.mp4",
      "segment_sec": 10.0,
      "queue_to_db_sec": 93.764,
      "success": false,
      "time_sec": 90.77,
      "vlm_time_sec": 0.0,
      "yolo_reid_time_sec": 0.0,
      "put_time_sec": 1773065326.58,
      "batch_upload_start_sec": 1773065326.58,
      "batch_upload_end_sec": 1773065420.344,
      "wait_in_queue_sec": 0.0,
      "client_upload_plus_backend_sec": 93.764,
      "api_batch_process_time_sec": 91.54,
      "api_batch_total_time_sec": 91.88,
      "time_breakdown": "queue_to_db_sec = wait_in_queue_sec + client_upload_plus_backend_sec (0.0 + 93.764 = 93.764). time_sec = 後端該段 total_api_time（同一批內多段共用同一批處理時間）。"
    },
    {
      "video_id": "RTSP_03",
      "filename": "RTSP_03_2.mp4",
      "segment_sec": 10.0,
      "queue_to_db_sec": 120.949,
      "success": false,
      "time_sec": 119.75,
      "vlm_time_sec": 0.0,
      "yolo_reid_time_sec": 0.0,
      "put_time_sec": 1773065299.396,
      "batch_upload_start_sec": 1773065299.397,
      "batch_upload_end_sec": 1773065420.345,
      "wait_in_queue_sec": 0.002,
      "client_upload_plus_backend_sec": 120.948,
      "api_batch_process_time_sec": 120.51,
      "api_batch_total_time_sec": 120.6,
      "time_breakdown": "queue_to_db_sec = wait_in_queue_sec + client_upload_plus_backend_sec (0.002 + 120.948 = 120.949). time_sec = 後端該段 total_api_time（同一批內多段共用同一批處理時間）。"
    },
    {
      "video_id": "RTSP_03",
      "filename": "RTSP_03_5.mp4",
      "segment_sec": 10.0,
      "queue_to_db_sec": 80.031,
      "success": false,
      "time_sec": 78.19,
      "vlm_time_sec": 0.0,
      "yolo_reid_time_sec": 0.0,
      "put_time_sec": 1773065340.314,
      "batch_upload_start_sec": 1773065340.314,
      "batch_upload_end_sec": 1773065420.345,
      "wait_in_queue_sec": 0.0,
      "client_upload_plus_backend_sec": 80.031,
      "api_batch_process_time_sec": 78.95,
      "api_batch_total_time_sec": 78.96,
      "time_breakdown": "queue_to_db_sec = wait_in_queue_sec + client_upload_plus_backend_sec (0.0 + 80.031 = 80.031). time_sec = 後端該段 total_api_time（同一批內多段共用同一批處理時間）。"
    }
  ],
  "summary": {
    "total_segments": 24,
    "success_count": 0,
    "fail_count": 24,
    "avg_process_duration_sec": 64.808,
    "avg_wait_in_queue_time": 0.0,
    "avg_queue_to_db_sec": 65.895,
    "avg_client_upload_plus_backend_sec": 65.895,
    "time_breakdown_legend": {
      "queue_to_db_sec": "從「該段放入佇列 put_time_sec」到「該批 API 回傳 batch_upload_end_sec」的秒數。",
      "formula_queue_to_db": "queue_to_db_sec = wait_in_queue_sec + client_upload_plus_backend_sec",
      "wait_in_queue_sec": "從 put_time_sec 到 batch_upload_start_sec：該段在佇列中等候直到 worker 開始送這批請求。",
      "client_upload_plus_backend_sec": "從 batch_upload_start_sec 到 batch_upload_end_sec：客戶端開始 POST 到收到回應（含上傳、後端處理、下載）。同一批的每段此值相同。",
      "time_sec": "後端回傳的 total_api_time。batch 模式下同一批內多段共用「整批」的處理時間，故同一批的 time_sec 會相同。",
      "vlm_time_sec": "後端該段 VLM 耗時（batch 路徑目前多為 null）。",
      "yolo_reid_time_sec": "後端該段 YOLO+ReID 耗時（batch 路徑目前多為 null）。",
      "api_batch_process_time_sec": "該批 API 回傳的 process_time_sec（後端跑 run_full_pipeline 的 t2-t1）。",
      "api_batch_total_time_sec": "該批 API 回傳的 total_time_sec（後端整次請求 t2-t0）。"
    }
  }
}